trapdoor/__init__.py
trapdoor/configfile.py
trapdoor/tests/__init__.py
trapdoor/tests/test_trapdoor.py
trapdoor/trapdoor.py
trapdoor/utils/__init__.py
trapdoor/utils/fs.py
trapdoor/utils/selectors.py
trapdoor-0.6.0.dist-info/METADATA
trapdoor-0.6.0.dist-info/WHEEL
trapdoor-0.6.0.dist-info/RECORD
