Metadata-Version: 2.1
Name: trapdoor
Version: 0.6.0
Summary: Turn-key configuration file management for Python packages.
License: MIT
Author: Clay McLeod
Author-email: clay.l.mcleod@gmail.com
Requires-Python: >=3.7
Classifier: License :: OSI Approved :: MIT License
Classifier: Programming Language :: Python :: 3
Classifier: Programming Language :: Python :: 3.7
Classifier: Programming Language :: Python :: 3.8
Classifier: Programming Language :: Python :: 3.9
Classifier: Programming Language :: Python :: 3.10
Classifier: Programming Language :: Python :: 3.11
Requires-Dist: toml (>=0.10.2,<0.11.0)
